README.md
setup.py
my_bert/__init__.py
my_bert/backend.py
my_bert/layers.py
my_bert/models.py
my_bert/optimizers.py
my_bert/snippets.py
my_bert/tokenizers.py
my_bert.egg-info/PKG-INFO
my_bert.egg-info/SOURCES.txt
my_bert.egg-info/dependency_links.txt
my_bert.egg-info/top_level.txt