Metadata-Version: 2.1
Name: my-bert
Version: 0.1.0
Summary: just a bert tool
Home-page: https://github.com/hzfei/my-bert
Author: hzfei
Author-email: 1027551108@qq.com
License: UNKNOWN
Platform: UNKNOWN
Classifier: Programming Language :: Python :: 3
Classifier: License :: OSI Approved :: MIT License
Classifier: Operating System :: OS Independent
